{
    "dt": 0.04,
    "total_time": 14.119999999999875,
    "n_active": 0,
    "m_kill": 1e-14,
    "v_kill": 3000.0,
    "h_kill": 10194.0,
    "len_kill": -1000.0,
    "h_init": 180000.0,
    "P_0m": 3030.0,
    "dens_co": [
        1.8711620767711044,
        -229.83144250499456,
        5449.3613450408175,
        -74515.89679368827,
        446470.0587911939,
        -1011380.1500935825,
        310222.8742728522
    ],
    "r_earth": 6367808.358943568,
    "total_fragments": 883,
    "wake_psf": 3.0,
    "wake_extension": 200.0,
    "rho": 1500.0,
    "m_init": 2790000.0,
    "v_init": 15200.0,
    "shape_factor": 0.8,
    "sigma": 5e-09,
    "zenith_angle": 0.6065193683605494,
    "gamma": 1.0,
    "rho_grain": 3500.0,
    "lum_eff_type": 7,
    "lum_eff": 0.7,
    "mu": 3.8180000000000003e-26,
    "erosion_on": false,
    "erosion_bins_per_10mass": 2,
    "erosion_height_start": 75177.0,
    "erosion_coeff": 3.3e-07,
    "erosion_height_change": 13194.0,
    "erosion_coeff_change": 3.3e-07,
    "erosion_rho_change": 1500.0,
    "erosion_sigma_change": 5e-09,
    "erosion_mass_index": 2.5,
    "erosion_mass_min": 1e-11,
    "erosion_mass_max": 5e-10,
    "disruption_on": false,
    "compressive_strength": 2000.0,
    "disruption_height": null,
    "disruption_erosion_coeff": 3.3e-07,
    "disruption_mass_index": 2.0,
    "disruption_mass_min_ratio": 0.01,
    "disruption_mass_max_ratio": 0.1,
    "disruption_mass_grain_ratio": 0.25,
    "fragmentation_on": true,
    "fragmentation_show_individual_lcs": true,
    "fragmentation_entries": [
        {
            "id": 0,
            "done": true,
            "frag_type": "D",
            "upward_only": false,
            "height": 81660.0,
            "number": null,
            "mass_percent": 13.88,
            "sigma": null,
            "gamma": null,
            "erosion_coeff": null,
            "grain_mass_min": 0.0133,
            "grain_mass_max": 0.0277,
            "mass_index": 2.5,
            "time": 7.880000000000006,
            "dyn_pressure": 3013.7369631984975,
            "velocity": 15199.951314588292,
            "parent_mass": 2789986.8837742866,
            "mass": 387250.17946787097,
            "final_mass": null,
            "main_time_data": [],
            "main_height_data": [],
            "main_luminosity": [],
            "main_abs_mag": [],
            "main_tau_over_lum": [],
            "main_tau": [],
            "grains_time_data": [],
            "grains_height_data": [],
            "grains_luminosity": [],
            "grains_abs_mag": [],
            "grains_tau_over_lum": [],
            "grains_tau": []
        },
        {
            "id": 1,
            "done": true,
            "frag_type": "EF",
            "upward_only": false,
            "height": 63710.0,
            "number": 1,
            "mass_percent": 89.77,
            "sigma": null,
            "gamma": null,
            "erosion_coeff": 6.577e-07,
            "grain_mass_min": 0.00014,
            "grain_mass_max": 0.645,
            "mass_index": 2.5,
            "time": 9.319999999999977,
            "dyn_pressure": 53862.389586982645,
            "velocity": 15198.697904082053,
            "parent_mass": 2402507.396046494,
            "mass": 2156730.889430938,
            "final_mass": 0.001474841301958356,
            "main_time_data": [],
            "main_height_data": [],
            "main_luminosity": [],
            "main_abs_mag": [],
            "main_tau_over_lum": [],
            "main_tau": [],
            "grains_time_data": [],
            "grains_height_data": [],
            "grains_luminosity": [],
            "grains_abs_mag": [],
            "grains_tau_over_lum": [],
            "grains_tau": []
        },
        {
            "id": 2,
            "done": true,
            "frag_type": "EF",
            "upward_only": false,
            "height": 47780.0,
            "number": 1,
            "mass_percent": 42.49,
            "sigma": null,
            "gamma": null,
            "erosion_coeff": 2.396e-06,
            "grain_mass_min": 0.00114,
            "grain_mass_max": 0.138,
            "mass_index": 2.5,
            "time": 10.639999999999949,
            "dyn_pressure": 439218.9609609435,
            "velocity": 15173.418948475924,
            "parent_mass": 245305.11116480816,
            "mass": 104230.14173392698,
            "final_mass": null,
            "main_time_data": [],
            "main_height_data": [],
            "main_luminosity": [],
            "main_abs_mag": [],
            "main_tau_over_lum": [],
            "main_tau": [],
            "grains_time_data": [],
            "grains_height_data": [],
            "grains_luminosity": [],
            "grains_abs_mag": [],
            "grains_tau_over_lum": [],
            "grains_tau": []
        },
        {
            "id": 3,
            "done": true,
            "frag_type": "EF",
            "upward_only": false,
            "height": 37780.0,
            "number": 1,
            "mass_percent": 24.64,
            "sigma": null,
            "gamma": null,
            "erosion_coeff": 5.3255e-06,
            "grain_mass_min": 0.229,
            "grain_mass_max": 0.508,
            "mass_index": 2.5,
            "time": 11.439999999999932,
            "dyn_pressure": 1349306.2755636976,
            "velocity": 15095.045505196127,
            "parent_mass": 140240.36910181135,
            "mass": 34555.226946686314,
            "final_mass": null,
            "main_time_data": [],
            "main_height_data": [],
            "main_luminosity": [],
            "main_abs_mag": [],
            "main_tau_over_lum": [],
            "main_tau": [],
            "grains_time_data": [],
            "grains_height_data": [],
            "grains_luminosity": [],
            "grains_abs_mag": [],
            "grains_tau_over_lum": [],
            "grains_tau": []
        },
        {
            "id": 4,
            "done": true,
            "frag_type": "EF",
            "upward_only": false,
            "height": 35490.0,
            "number": 1,
            "mass_percent": 32.29,
            "sigma": null,
            "gamma": null,
            "erosion_coeff": 1.3369e-06,
            "grain_mass_min": 0.012,
            "grain_mass_max": 0.0723,
            "mass_index": 2.5,
            "time": 11.599999999999929,
            "dyn_pressure": 1695755.3017149048,
            "velocity": 15062.80636889904,
            "parent_mass": 105428.33507352369,
            "mass": 34042.809395240794,
            "final_mass": null,
            "main_time_data": [],
            "main_height_data": [],
            "main_luminosity": [],
            "main_abs_mag": [],
            "main_tau_over_lum": [],
            "main_tau": [],
            "grains_time_data": [],
            "grains_height_data": [],
            "grains_luminosity": [],
            "grains_abs_mag": [],
            "grains_tau_over_lum": [],
            "grains_tau": []
        }
    ],
    "fragmentation_file_name": "metsim_fragmentation.txt",
    "electron_density_meas_ht": -1000.0,
    "electron_density_meas_q": -1.0,
    "erosion_beg_vel": null,
    "erosion_beg_mass": null,
    "erosion_beg_dyn_press": null,
    "mass_at_erosion_change": null,
    "energy_per_cs_before_erosion": null,
    "energy_per_mass_before_erosion": null,
    "main_mass_exhaustion_ht": 10131.12283573177,
    "main_bottom_ht": 10131.12283573177
}